commandable
