Metadata-Version: 1.1
Name: nci-python-commands
Version: 1.0.7
Summary: An object orientated CLI command library
Home-page: https://github.com/newcraftgroup/nci-python-commands
Author: NEWCRAFT
Author-email: cedric.le.varlet@newcraftgroup.com
License: Apache License, Version 2.0
Keywords: development command commandtool terminal cli
Platform: UNKNOWN
Classifier: Development Status :: 4 - Beta
Classifier: Intended Audience :: Developers
Classifier: Programming Language :: Python :: 3
Classifier: Programming Language :: Python :: 3.2
Classifier: Programming Language :: Python :: 3.3
Classifier: Programming Language :: Python :: 3.4
Classifier: Programming Language :: Python :: 3.5
Classifier: Programming Language :: Python :: 3.6
